{
    "_checkpoint": {
        "global_record": {
            "index": -1,
            "infractions": {
                "collisions_layout": 0.0,
                "collisions_pedestrian": 0.0,
                "collisions_vehicle": 10.18752211455509,
                "outside_route_lanes": 0.0,
                "red_light": 0.0,
                "route_dev": 0.0,
                "route_timeout": 5.093761057277545,
                "stop_infraction": 0.0,
                "vehicle_blocked": 0.0
            },
            "meta": {
                "duration_game": 261.1000038906932,
                "duration_system": 547.7129461765289,
                "exceptions": [
                    [
                        "RouteScenario_36",
                        0,
                        "Failed - Agent timed out"
                    ]
                ],
                "total_length": 315.1736557045976
            },
            "route_id": -1,
            "scores": {
                "score_composed": 22.42404843463312,
                "score_penalty": 0.36,
                "score_route": 62.28902342953645
            },
            "scores_std_dev": {
                "score_composed": "NaN",
                "score_penalty": "NaN",
                "score_route": "NaN"
            },
            "status": "Failed"
        },
        "progress": [
            1,
            1
        ],
        "records": [
            {
                "index": 0,
                "infractions": {
                    "collisions_layout": [],
                    "collisions_pedestrian": [],
                    "collisions_vehicle": [
                        "Agent collided against object with type=vehicle.volkswagen.t2 and id=20671 at (x=-1.732, y=301.735, z=0.253)",
                        "Agent collided against object with type=vehicle.dodge_charger.police and id=20743 at (x=-4.258, y=299.05, z=0.254)"
                    ],
                    "outside_route_lanes": [],
                    "red_light": [],
                    "route_dev": [],
                    "route_timeout": [
                        "Route timeout."
                    ],
                    "stop_infraction": [],
                    "vehicle_blocked": []
                },
                "meta": {
                    "duration_game": 261.1000038906932,
                    "duration_system": 547.7129461765289,
                    "route_length": 315.1736557045976
                },
                "route_id": "RouteScenario_36",
                "scores": {
                    "score_composed": 22.42404843463312,
                    "score_penalty": 0.36,
                    "score_route": 62.28902342953645
                },
                "status": "Failed - Agent timed out"
            }
        ]
    },
    "eligible": true,
    "entry_status": "Finished with agent errors",
    "labels": [
        "Avg. driving score",
        "Avg. route completion",
        "Avg. infraction penalty",
        "Collisions with pedestrians",
        "Collisions with vehicles",
        "Collisions with layout",
        "Red lights infractions",
        "Stop sign infractions",
        "Off-road infractions",
        "Route deviations",
        "Route timeouts",
        "Agent blocked"
    ],
    "sensors": [
        "carla_camera",
        "carla_imu",
        "carla_gnss",
        "carla_speedometer",
        "carla_lidar"
    ],
    "values": [
        "22.424",
        "62.289",
        "0.360",
        "0.000",
        "10.188",
        "0.000",
        "0.000",
        "0.000",
        "0.000",
        "0.000",
        "5.094",
        "0.000"
    ]
}